RsCmwWlanSig/RsCmwWlanSig.py
RsCmwWlanSig/__init__.py
RsCmwWlanSig/enums.py
RsCmwWlanSig/repcap.py
RsCmwWlanSig/CustomFiles/__init__.py
RsCmwWlanSig/CustomFiles/events.py
RsCmwWlanSig/CustomFiles/reliability.py
RsCmwWlanSig/CustomFiles/utilities.py
RsCmwWlanSig/Implementations/PackRate.py
RsCmwWlanSig/Implementations/__init__.py
RsCmwWlanSig/Implementations/Call/__init__.py
RsCmwWlanSig/Implementations/Call/Action/__init__.py
RsCmwWlanSig/Implementations/Call/Action/Station/Connect.py
RsCmwWlanSig/Implementations/Call/Action/Station/Reconnect.py
RsCmwWlanSig/Implementations/Call/Action/Station/__init__.py
RsCmwWlanSig/Implementations/Call/Action/Wdirect/Sconnection.py
RsCmwWlanSig/Implementations/Call/Action/Wdirect/__init__.py
RsCmwWlanSig/Implementations/Call/Action/Wps/Sconnection.py
RsCmwWlanSig/Implementations/Call/Action/Wps/__init__.py
RsCmwWlanSig/Implementations/Call/Sta/__init__.py
RsCmwWlanSig/Implementations/Call/Sta/Action/Disconnect.py
RsCmwWlanSig/Implementations/Call/Sta/Action/__init__.py
RsCmwWlanSig/Implementations/Clean/Elogging.py
RsCmwWlanSig/Implementations/Clean/__init__.py
RsCmwWlanSig/Implementations/Configure/Edau.py
RsCmwWlanSig/Implementations/Configure/HetBased.py
RsCmwWlanSig/Implementations/Configure/IpvSix.py
RsCmwWlanSig/Implementations/Configure/__init__.py
RsCmwWlanSig/Implementations/Configure/Connection/Aid.py
RsCmwWlanSig/Implementations/Configure/Connection/DyFragment.py
RsCmwWlanSig/Implementations/Configure/Connection/Hemac.py
RsCmwWlanSig/Implementations/Configure/Connection/MfDef.py
RsCmwWlanSig/Implementations/Configure/Connection/OobDiscovery.py
RsCmwWlanSig/Implementations/Configure/Connection/Qos.py
RsCmwWlanSig/Implementations/Configure/Connection/Station.py
RsCmwWlanSig/Implementations/Configure/Connection/TpControl.py
RsCmwWlanSig/Implementations/Configure/Connection/Twt.py
RsCmwWlanSig/Implementations/Configure/Connection/__init__.py
RsCmwWlanSig/Implementations/Configure/Connection/Association/Disass.py
RsCmwWlanSig-4.0.110.dist-info/METADATA
RsCmwWlanSig-4.0.110.dist-info/WHEEL
RsCmwWlanSig-4.0.110.dist-info/top_level.txt
RsCmwWlanSig-4.0.110.dist-info/RECORD
